autopyreadme/__init__.py
autopyreadme/readme.py
autopyreadme/create_readme_json/__init__.py
autopyreadme/create_readme_json/create_readme_json.py
autopyreadme/create_readme_md/__init__.py
autopyreadme/create_readme_md/create_readme_md.py
autopyreadme-0.0.2.dist-info/METADATA
autopyreadme-0.0.2.dist-info/WHEEL
autopyreadme-0.0.2.dist-info/licenses/LICENSE
autopyreadme-0.0.2.dist-info/RECORD
