Metadata-Version: 2.1
Name: autopyreadme
Version: 0.0.2
Summary: It is an Automated tool for generating Readme for python projects
Project-URL: Github, https://github.com/nishant-ai/auto_readme
Author-email: Nishant Sharma <nishant-ai@outlook.com>
License: MIT License
Classifier: License :: OSI Approved :: MIT License
Classifier: Operating System :: OS Independent
Classifier: Programming Language :: Python :: 3
Requires-Python: >=3.7
